<?xml version="1.0" encoding="ISO-8859-1" standalone="yes"?>
<TrafficMatrixFile xsi:noNamespaceSchemaLocation="http://totem.run.montefiore.ulg.ac.be/Schema/TrafficMatrix-v1_2.xsd" xmlns:xsi="http://www.w3.org/2001/XMLSchema-instance">
    <IntraTM ASID="11537">
        <src id="ATLA-M5">
            <dst id="ATLA-M5">0</dst>
            <dst id="ATLAng">5659.51466666667</dst>
            <dst id="CHINng">169.237333333333</dst>
            <dst id="DNVRng">0</dst>
            <dst id="HSTNng">0</dst>
            <dst id="IPLSng">26.6666666666667</dst>
            <dst id="KSCYng">609.389333333333</dst>
            <dst id="LOSAng">1154.51466666667</dst>
            <dst id="NYCMng">106.026666666667</dst>
            <dst id="SNVAng">0</dst>
            <dst id="STTLng">95.68</dst>
            <dst id="WASHng">340.189333333333</dst>
        </src>
        <src id="ATLAng">
            <dst id="ATLA-M5">380.04</dst>
            <dst id="ATLAng">24562.008</dst>
            <dst id="CHINng">9373.54133333333</dst>
            <dst id="DNVRng">7220.09866666667</dst>
            <dst id="HSTNng">8072.17333333333</dst>
            <dst id="IPLSng">10290.3333333333</dst>
            <dst id="KSCYng">676.026666666667</dst>
            <dst id="LOSAng">24544.744</dst>
            <dst id="NYCMng">4391.136</dst>
            <dst id="SNVAng">665.333333333333</dst>
            <dst id="STTLng">8004.41866666667</dst>
            <dst id="WASHng">38182.1493333333</dst>
        </src>
        <src id="CHINng">
            <dst id="ATLA-M5">136.576</dst>
            <dst id="ATLAng">11040.0986666667</dst>
            <dst id="CHINng">65760.6693333333</dst>
            <dst id="DNVRng">21367.3786666667</dst>
            <dst id="HSTNng">7534.384</dst>
            <dst id="IPLSng">31964.3093333333</dst>
            <dst id="KSCYng">9282.47466666667</dst>
            <dst id="LOSAng">57157.7173333333</dst>
            <dst id="NYCMng">9521.44533333333</dst>
            <dst id="SNVAng">3491.304</dst>
            <dst id="STTLng">9976.05866666667</dst>
            <dst id="WASHng">91694.5013333333</dst>
        </src>
        <src id="DNVRng">
            <dst id="ATLA-M5">88.8026666666667</dst>
            <dst id="ATLAng">5557.048</dst>
            <dst id="CHINng">42324.56</dst>
            <dst id="DNVRng">27293.336</dst>
            <dst id="HSTNng">23250.1626666667</dst>
            <dst id="IPLSng">16191.84</dst>
            <dst id="KSCYng">21374.2106666667</dst>
            <dst id="LOSAng">7146.44</dst>
            <dst id="NYCMng">19520.984</dst>
            <dst id="SNVAng">10442.6133333333</dst>
            <dst id="STTLng">16095.7626666667</dst>
            <dst id="WASHng">16617.9946666667</dst>
        </src>
        <src id="HSTNng">
            <dst id="ATLA-M5">194.88</dst>
            <dst id="ATLAng">14184.352</dst>
            <dst id="CHINng">11671.3066666667</dst>
            <dst id="DNVRng">1719.52533333333</dst>
            <dst id="HSTNng">13331.0986666667</dst>
            <dst id="IPLSng">870.602666666667</dst>
            <dst id="KSCYng">7141.976</dst>
            <dst id="LOSAng">10360.2266666667</dst>
            <dst id="NYCMng">2766.04</dst>
            <dst id="SNVAng">26.6666666666667</dst>
            <dst id="STTLng">3954.70133333333</dst>
            <dst id="WASHng">3626.23466666667</dst>
        </src>
        <src id="IPLSng">
            <dst id="ATLA-M5">0</dst>
            <dst id="ATLAng">13420.824</dst>
            <dst id="CHINng">72330.8426666667</dst>
            <dst id="DNVRng">3879.82933333333</dst>
            <dst id="HSTNng">4014.02933333333</dst>
            <dst id="IPLSng">8957.04</dst>
            <dst id="KSCYng">3868.992</dst>
            <dst id="LOSAng">48138.7253333333</dst>
            <dst id="NYCMng">24240.5306666667</dst>
            <dst id="SNVAng">961.442666666667</dst>
            <dst id="STTLng">8655.23466666667</dst>
            <dst id="WASHng">11861.5173333333</dst>
        </src>
        <src id="KSCYng">
            <dst id="ATLA-M5">0</dst>
            <dst id="ATLAng">2318.8</dst>
            <dst id="CHINng">23068.2773333333</dst>
            <dst id="DNVRng">10325.6826666667</dst>
            <dst id="HSTNng">2891.30133333333</dst>
            <dst id="IPLSng">13966.9493333333</dst>
            <dst id="KSCYng">11928.0586666667</dst>
            <dst id="LOSAng">8311.544</dst>
            <dst id="NYCMng">8557.54666666667</dst>
            <dst id="SNVAng">125.696</dst>
            <dst id="STTLng">1808.82133333333</dst>
            <dst id="WASHng">10484.9653333333</dst>
        </src>
        <src id="LOSAng">
            <dst id="ATLA-M5">1633.968</dst>
            <dst id="ATLAng">23133.7706666667</dst>
            <dst id="CHINng">96373.312</dst>
            <dst id="DNVRng">15225.672</dst>
            <dst id="HSTNng">9793.31733333333</dst>
            <dst id="IPLSng">52706.2746666667</dst>
            <dst id="KSCYng">6872.024</dst>
            <dst id="LOSAng">18329.52</dst>
            <dst id="NYCMng">106401.826666667</dst>
            <dst id="SNVAng">17280.928</dst>
            <dst id="STTLng">48724.0133333333</dst>
            <dst id="WASHng">131834.461333333</dst>
        </src>
        <src id="NYCMng">
            <dst id="ATLA-M5">903.741333333333</dst>
            <dst id="ATLAng">32064.504</dst>
            <dst id="CHINng">120380.808</dst>
            <dst id="DNVRng">32281.8986666667</dst>
            <dst id="HSTNng">12271.0346666667</dst>
            <dst id="IPLSng">45343.0666666667</dst>
            <dst id="KSCYng">12766.664</dst>
            <dst id="LOSAng">82483.344</dst>
            <dst id="NYCMng">108011.832</dst>
            <dst id="SNVAng">4598.38933333333</dst>
            <dst id="STTLng">36630.0666666667</dst>
            <dst id="WASHng">44703.2586666667</dst>
        </src>
        <src id="SNVAng">
            <dst id="ATLA-M5">0</dst>
            <dst id="ATLAng">53.3333333333333</dst>
            <dst id="CHINng">407.426666666667</dst>
            <dst id="DNVRng">13042.5546666667</dst>
            <dst id="HSTNng">26.6666666666667</dst>
            <dst id="IPLSng">1429.264</dst>
            <dst id="KSCYng">53.3333333333333</dst>
            <dst id="LOSAng">12216.072</dst>
            <dst id="NYCMng">194.464</dst>
            <dst id="SNVAng">6953.304</dst>
            <dst id="STTLng">8008.55466666667</dst>
            <dst id="WASHng">80</dst>
        </src>
        <src id="STTLng">
            <dst id="ATLA-M5">0</dst>
            <dst id="ATLAng">10323.2693333333</dst>
            <dst id="CHINng">18187.9306666667</dst>
            <dst id="DNVRng">4991.54666666667</dst>
            <dst id="HSTNng">1366.09066666667</dst>
            <dst id="IPLSng">10015.544</dst>
            <dst id="KSCYng">2185.488</dst>
            <dst id="LOSAng">33780.024</dst>
            <dst id="NYCMng">11386.08</dst>
            <dst id="SNVAng">3850.856</dst>
            <dst id="STTLng">5292.05333333333</dst>
            <dst id="WASHng">10229.856</dst>
        </src>
        <src id="WASHng">
            <dst id="ATLA-M5">57.3493333333333</dst>
            <dst id="ATLAng">120924.565333333</dst>
            <dst id="CHINng">99039.3866666666</dst>
            <dst id="DNVRng">32237.9013333333</dst>
            <dst id="HSTNng">21618.2906666667</dst>
            <dst id="IPLSng">48374.7786666667</dst>
            <dst id="KSCYng">15202.856</dst>
            <dst id="LOSAng">130502.813333333</dst>
            <dst id="NYCMng">115279.810666667</dst>
            <dst id="SNVAng">2481.80266666667</dst>
            <dst id="STTLng">42730.1493333333</dst>
            <dst id="WASHng">205121.301333333</dst>
        </src>
    </IntraTM>
</TrafficMatrixFile>
