<?xml version="1.0" encoding="ISO-8859-1" standalone="yes"?>
<TrafficMatrixFile xsi:noNamespaceSchemaLocation="http://totem.run.montefiore.ulg.ac.be/Schema/TrafficMatrix-v1_2.xsd" xmlns:xsi="http://www.w3.org/2001/XMLSchema-instance">
    <IntraTM ASID="11537">
        <src id="ATLA-M5">
            <dst id="ATLA-M5">113.888</dst>
            <dst id="ATLAng">245.562666666667</dst>
            <dst id="CHINng">652.610666666667</dst>
            <dst id="DNVRng">0</dst>
            <dst id="HSTNng">980.538666666667</dst>
            <dst id="IPLSng">321.104</dst>
            <dst id="KSCYng">86.3413333333333</dst>
            <dst id="LOSAng">0</dst>
            <dst id="NYCMng">1267.34666666667</dst>
            <dst id="SNVAng">0</dst>
            <dst id="STTLng">0</dst>
            <dst id="WASHng">3988.168</dst>
        </src>
        <src id="ATLAng">
            <dst id="ATLA-M5">0</dst>
            <dst id="ATLAng">27515.4053333333</dst>
            <dst id="CHINng">35236.976</dst>
            <dst id="DNVRng">132.370666666667</dst>
            <dst id="HSTNng">32912.6586666667</dst>
            <dst id="IPLSng">33989.8506666667</dst>
            <dst id="KSCYng">5098.16266666667</dst>
            <dst id="LOSAng">0</dst>
            <dst id="NYCMng">18674.1173333333</dst>
            <dst id="SNVAng">0</dst>
            <dst id="STTLng">180.277333333333</dst>
            <dst id="WASHng">47791.416</dst>
        </src>
        <src id="CHINng">
            <dst id="ATLA-M5">0</dst>
            <dst id="ATLAng">41566.0133333333</dst>
            <dst id="CHINng">89361.6266666667</dst>
            <dst id="DNVRng">12995.8933333333</dst>
            <dst id="HSTNng">144609.877333333</dst>
            <dst id="IPLSng">56911.3733333333</dst>
            <dst id="KSCYng">17087.4853333333</dst>
            <dst id="LOSAng">110.293333333333</dst>
            <dst id="NYCMng">44526.2293333333</dst>
            <dst id="SNVAng">0</dst>
            <dst id="STTLng">1066.176</dst>
            <dst id="WASHng">46987.5653333333</dst>
        </src>
        <src id="DNVRng">
            <dst id="ATLA-M5">0</dst>
            <dst id="ATLAng">7181.944</dst>
            <dst id="CHINng">60232.7893333333</dst>
            <dst id="DNVRng">3657.42933333333</dst>
            <dst id="HSTNng">47173.12</dst>
            <dst id="IPLSng">26829.288</dst>
            <dst id="KSCYng">14365.4133333333</dst>
            <dst id="LOSAng">0</dst>
            <dst id="NYCMng">17338.3706666667</dst>
            <dst id="SNVAng">14515.752</dst>
            <dst id="STTLng">2519.58133333333</dst>
            <dst id="WASHng">40512.376</dst>
        </src>
        <src id="HSTNng">
            <dst id="ATLA-M5">0</dst>
            <dst id="ATLAng">35926.5893333333</dst>
            <dst id="CHINng">1762.784</dst>
            <dst id="DNVRng">26.6666666666667</dst>
            <dst id="HSTNng">152445.962666667</dst>
            <dst id="IPLSng">0</dst>
            <dst id="KSCYng">119.885333333333</dst>
            <dst id="LOSAng">34.08</dst>
            <dst id="NYCMng">8233.33066666667</dst>
            <dst id="SNVAng">53.3333333333333</dst>
            <dst id="STTLng">268.704</dst>
            <dst id="WASHng">104281.434666667</dst>
        </src>
        <src id="IPLSng">
            <dst id="ATLA-M5">0</dst>
            <dst id="ATLAng">22116.04</dst>
            <dst id="CHINng">168386.490666667</dst>
            <dst id="DNVRng">24291.5546666667</dst>
            <dst id="HSTNng">93513.9466666666</dst>
            <dst id="IPLSng">32364.408</dst>
            <dst id="KSCYng">22257.2106666667</dst>
            <dst id="LOSAng">26.6666666666667</dst>
            <dst id="NYCMng">83747.864</dst>
            <dst id="SNVAng">4798.41066666667</dst>
            <dst id="STTLng">276.405333333333</dst>
            <dst id="WASHng">46002.3946666667</dst>
        </src>
        <src id="KSCYng">
            <dst id="ATLA-M5">0</dst>
            <dst id="ATLAng">10224.6826666667</dst>
            <dst id="CHINng">33215.032</dst>
            <dst id="DNVRng">9701.912</dst>
            <dst id="HSTNng">20320.7093333333</dst>
            <dst id="IPLSng">13545.2293333333</dst>
            <dst id="KSCYng">5496.12266666667</dst>
            <dst id="LOSAng">26.6666666666667</dst>
            <dst id="NYCMng">12415.1973333333</dst>
            <dst id="SNVAng">26.6666666666667</dst>
            <dst id="STTLng">105.981333333333</dst>
            <dst id="WASHng">12885.7493333333</dst>
        </src>
        <src id="LOSAng">
            <dst id="ATLA-M5">0</dst>
            <dst id="ATLAng">28713.7173333333</dst>
            <dst id="CHINng">8714.56533333333</dst>
            <dst id="DNVRng">17618.5706666667</dst>
            <dst id="HSTNng">174608.250666667</dst>
            <dst id="IPLSng">1462.49333333333</dst>
            <dst id="KSCYng">202.869333333333</dst>
            <dst id="LOSAng">16242.8613333333</dst>
            <dst id="NYCMng">66720.5733333333</dst>
            <dst id="SNVAng">10544.3333333333</dst>
            <dst id="STTLng">29085.5146666667</dst>
            <dst id="WASHng">98472.848</dst>
        </src>
        <src id="NYCMng">
            <dst id="ATLA-M5">0</dst>
            <dst id="ATLAng">37849.1386666667</dst>
            <dst id="CHINng">119434.058666667</dst>
            <dst id="DNVRng">38172.656</dst>
            <dst id="HSTNng">131792.341333333</dst>
            <dst id="IPLSng">52898.6506666667</dst>
            <dst id="KSCYng">20378.1813333333</dst>
            <dst id="LOSAng">207.658666666667</dst>
            <dst id="NYCMng">229599.68</dst>
            <dst id="SNVAng">106.666666666667</dst>
            <dst id="STTLng">7506.384</dst>
            <dst id="WASHng">139147.816</dst>
        </src>
        <src id="SNVAng">
            <dst id="ATLA-M5">0</dst>
            <dst id="ATLAng">3499.42666666667</dst>
            <dst id="CHINng">196.522666666667</dst>
            <dst id="DNVRng">10167.816</dst>
            <dst id="HSTNng">7559.17333333333</dst>
            <dst id="IPLSng">0</dst>
            <dst id="KSCYng">232.042666666667</dst>
            <dst id="LOSAng">40111.9226666667</dst>
            <dst id="NYCMng">5948.79733333333</dst>
            <dst id="SNVAng">13063.5306666667</dst>
            <dst id="STTLng">53667.5653333333</dst>
            <dst id="WASHng">679.181333333333</dst>
        </src>
        <src id="STTLng">
            <dst id="ATLA-M5">0</dst>
            <dst id="ATLAng">8729.60266666667</dst>
            <dst id="CHINng">25990.6826666667</dst>
            <dst id="DNVRng">5907.176</dst>
            <dst id="HSTNng">46772.5573333333</dst>
            <dst id="IPLSng">287.602666666667</dst>
            <dst id="KSCYng">5622.06133333333</dst>
            <dst id="LOSAng">27981.8</dst>
            <dst id="NYCMng">17915.8293333333</dst>
            <dst id="SNVAng">7000.824</dst>
            <dst id="STTLng">1937.904</dst>
            <dst id="WASHng">30660.5226666667</dst>
        </src>
        <src id="WASHng">
            <dst id="ATLA-M5">0</dst>
            <dst id="ATLAng">82957.4213333333</dst>
            <dst id="CHINng">111741.096</dst>
            <dst id="DNVRng">662.229333333333</dst>
            <dst id="HSTNng">296611.413333333</dst>
            <dst id="IPLSng">31000.5226666667</dst>
            <dst id="KSCYng">14174.5546666667</dst>
            <dst id="LOSAng">0</dst>
            <dst id="NYCMng">131320.944</dst>
            <dst id="SNVAng">53.3333333333333</dst>
            <dst id="STTLng">9194.48266666667</dst>
            <dst id="WASHng">247238.674666667</dst>
        </src>
    </IntraTM>
</TrafficMatrixFile>
